feynmodel/__init__.py
feynmodel/coupling.py
feynmodel/coupling_order.py
feynmodel/decay.py
feynmodel/feyn_model.py
feynmodel/form_factor.py
feynmodel/function.py
feynmodel/interface/__init__.py
feynmodel/interface/feynarts.py
feynmodel/interface/qgraf.py
feynmodel/interface/ufo.py
feynmodel/lorentz.py
feynmodel/model/__init__.py
feynmodel/model/mssm.py
feynmodel/model/sm.py
feynmodel/parameter.py
feynmodel/particle.py
feynmodel/ufo_base_class.py
feynmodel/util.py
feynmodel/vertex.py
feynmodel-0.0.11.dist-info/LICENSE
feynmodel-0.0.11.dist-info/METADATA
feynmodel-0.0.11.dist-info/WHEEL
feynmodel-0.0.11.dist-info/RECORD
