Metadata-Version: 2.3
Name: feynmodel
Version: 0.0.11
Summary: Models for constructing Feynman diagrams
Author: Alexander Puck Neuwirth
Author-email: alexander@neuwirth-informatik.de
Requires-Python: >=3.8,<4.0
Classifier: Programming Language :: Python :: 3
Classifier: Programming Language :: Python :: 3.8
Classifier: Programming Language :: Python :: 3.9
Classifier: Programming Language :: Python :: 3.10
Classifier: Programming Language :: Python :: 3.11
Classifier: Programming Language :: Python :: 3.12
Classifier: Programming Language :: Python :: 3.13
Requires-Dist: deprecated
Requires-Dist: deprecation
Requires-Dist: particle
Requires-Dist: smpl_doc
Requires-Dist: smpl_io
Requires-Dist: smpl_util
Requires-Dist: ufo_mssm
Requires-Dist: ufo_sm
Requires-Dist: xsdata[cli,lxml,soap]
Project-URL: Repository, https://github.com/APN-Pucky/feynmodel
